.gitignore
LICENSE.txt
MANIFEST
MANIFEST.in
README.md
setup.py
dist/django-ogone-1.0.0.zip
django_ogone/__init__.py
django_ogone/exceptions.py
django_ogone/forms.py
django_ogone/models.py
django_ogone/ogone.py
django_ogone/security.py
django_ogone/settings.py
django_ogone/signals.py
django_ogone/status_codes.py
django_ogone/tests.py
django_ogone.egg-info/PKG-INFO
django_ogone.egg-info/SOURCES.txt
django_ogone.egg-info/dependency_links.txt
django_ogone.egg-info/top_level.txt
examples/__init__.py
examples/models.py
examples/views.py