Metadata-Version: 1.0
Name: django-ogone
Version: 0.1
Summary: Python/Django client to the ogone payment system.
Home-page: http://github.com/tschellenbach/Django-ogone
Author: Thierry Schellenbach
Author-email: thierryschellenbach at googles great mail service
License:                     GNU GENERAL PUBLIC LICENSE
